ghost_stt/__init__.py
ghost_stt-0.1.dist-info/METADATA
ghost_stt-0.1.dist-info/WHEEL
ghost_stt-0.1.dist-info/top_level.txt
ghost_stt-0.1.dist-info/RECORD
