Metadata-Version: 2.1
Name: ghost-stt
Version: 0.1
Summary: this is speech to text package created by sarthak
Author: Sarthak
Author-email: sangrohasarthak06@gmail.com
